telefast/__init__.py
telefast/telefast.py
telefast-0.0.1rc0.dist-info/WHEEL
telefast-0.0.1rc0.dist-info/METADATA
telefast-0.0.1rc0.dist-info/RECORD
